{
  "main": {
    "id": "c5f21303d3bcaef6",
    "type": "split",
    "children": [
      {
        "id": "71aa14ce88bd54d1",
        "type": "tabs",
        "children": [
          {
            "id": "7f6b7ec82bd1961f",
            "type": "leaf",
            "state": {
              "type": "pdf",
              "state": {
                "file": "04/ФОЗИ/attachments/Physical Layer Components Security Risks in Optical Fiber Infrastructures.pdf"
              }
            }
          },
          {
            "id": "811e4e22ed734fd0",
            "type": "leaf",
            "state": {
              "type": "markdown",
              "state": {
                "file": "04/ФОЗИ/Оптический сплиттер.md",
                "mode": "source",
                "source": true
              }
            }
          },
          {
            "id": "020be38544c04d38",
            "type": "leaf",
            "state": {
              "type": "markdown",
              "state": {
                "file": "04/ФОЗИ/Сгибание оптоволокна.md",
                "mode": "preview",
                "source": true
              }
            }
          },
          {
            "id": "2c48f8e62f0e4a43",
            "type": "leaf",
            "state": {
              "type": "markdown",
              "state": {
                "file": "04/ФОЗИ/_Оптический канал утечки информации.md",
                "mode": "source",
                "source": true
              }
            }
          },
          {
            "id": "a515c9b4660b2985",
            "type": "leaf",
            "state": {
              "type": "pdf",
              "state": {
                "file": "04/ФОЗИ/attachments/OPTICAL NETWORK SECURITY TECHNICAL ANALYSIS OF FIBER TAPPING MECHANISMS AND METHODS FOR DETECTION & PREVENTION.pdf"
              }
            }
          }
        ],
        "currentTab": 3
      }
    ],
    "direction": "vertical"
  },
  "left": {
    "id": "6d788cc12ff4f818",
    "type": "split",
    "children": [
      {
        "id": "b81e60aff3a50159",
        "type": "tabs",
        "children": [
          {
            "id": "7e1236037668e8fa",
            "type": "leaf",
            "state": {
              "type": "file-explorer",
              "state": {
                "sortOrder": "alphabetical"
              }
            }
          },
          {
            "id": "6b797962c51bd9cb",
            "type": "leaf",
            "state": {
              "type": "search",
              "state": {
                "query": "",
                "matchingCase": false,
                "explainSearch": false,
                "collapseAll": false,
                "extraContext": false,
                "sortOrder": "alphabetical"
              }
            }
          },
          {
            "id": "a3988953270f985a",
            "type": "leaf",
            "state": {
              "type": "bookmarks",
              "state": {}
            }
          }
        ]
      }
    ],
    "direction": "horizontal",
    "width": 277.5,
    "collapsed": true
  },
  "right": {
    "id": "3b53b6f342632fe2",
    "type": "split",
    "children": [
      {
        "id": "27894d0c716abb18",
        "type": "tabs",
        "children": [
          {
            "id": "fdcd59221c64f85d",
            "type": "leaf",
            "state": {
              "type": "backlink",
              "state": {
                "file": "04/ФОЗИ/_Оптический канал утечки информации.md",
                "collapseAll": false,
                "extraContext": false,
                "sortOrder": "alphabetical",
                "showSearch": false,
                "searchQuery": "",
                "backlinkCollapsed": false,
                "unlinkedCollapsed": true
              }
            }
          },
          {
            "id": "0da3d204ce5bc4c4",
            "type": "leaf",
            "state": {
              "type": "outgoing-link",
              "state": {
                "file": "04/ФОЗИ/_Оптический канал утечки информации.md",
                "linksCollapsed": false,
                "unlinkedCollapsed": true
              }
            }
          },
          {
            "id": "e943d4a65792fd8e",
            "type": "leaf",
            "state": {
              "type": "tag",
              "state": {
                "sortOrder": "frequency",
                "useHierarchy": true
              }
            }
          },
          {
            "id": "0bb785fd8c164e51",
            "type": "leaf",
            "state": {
              "type": "outline",
              "state": {
                "file": "04/ФОЗИ/_Оптический канал утечки информации.md"
              }
            }
          },
          {
            "id": "d9199d74aea47691",
            "type": "leaf",
            "state": {
              "type": "all-properties",
              "state": {
                "sortOrder": "frequency",
                "showSearch": false,
                "searchQuery": ""
              }
            }
          }
        ],
        "currentTab": 3
      }
    ],
    "direction": "horizontal",
    "width": 300,
    "collapsed": true
  },
  "left-ribbon": {
    "hiddenItems": {
      "switcher:Open quick switcher": false,
      "graph:Open graph view": false,
      "canvas:Create new canvas": false,
      "daily-notes:Open today's daily note": false,
      "templates:Insert template": false,
      "command-palette:Open command palette": false,
      "markdown-importer:Open format converter": false,
      "workspaces:Manage workspace layouts": false,
      "obsidian-excalidraw-plugin:Create new drawing": false,
      "table-editor-obsidian:Advanced Tables Toolbar": false,
      "omnisearch:Omnisearch": false,
      "darlal-switcher-plus:Open in Headings Mode": false,
      "darlal-switcher-plus:Open Symbols for the active editor": false,
      "obsidian-focus-mode:Toggle Focus Mode (Shift + Click to show active pane only)": false
    }
  },
  "active": "2c48f8e62f0e4a43",
  "lastOpenFiles": [
    "04/ФОЗИ/Сгибание оптоволокна.md",
    "04/ФОЗИ/Оптический сплиттер.md",
    "04/ФОЗИ/_Оптический канал утечки информации.md",
    "_CW.pdf",
    "04/ФОЗИ/attachments/OPTICAL NETWORK SECURITY TECHNICAL ANALYSIS OF FIBER TAPPING MECHANISMS AND METHODS FOR DETECTION & PREVENTION.pdf",
    "04/ФОЗИ/attachments/Physical Layer Components Security Risks in Optical Fiber Infrastructures.pdf",
    "04/ФОЗИ/Типы подключений.md",
    "04/ФОЗИ/attachments/Скрытное подсоединие к оптоволокну_ методы и предосторожности.pdf",
    "04/ФОЗИ/attachments",
    "04/ФОЗИ/Index.md",
    "04/ФОЗИ/attachments/Vulnerabilities and Security Issues in Optical Networks.pdf",
    "04/ФОЗИ/OPTICAL NETWORK SECURITY TECHNICAL ANALYSIS OF FIBER TAPPING MECHANISMS AND METHODS FOR DETECTION & PREVENTION.pdf.crdownload",
    "04/ФОЗИ/attachments/Security threats and protection procedures for optical networks.pdf",
    "04/ФОЗИ/Security threats and protection procedures for optical networks.pdf.crdownload",
    "04/ФОЗИ/attachments/Secure Communication in Fiber-Optic Networks.pdf",
    "Untitled.md",
    "Untitled 1.md",
    "Welcome.md"
  ]
}